pba_client/__init__.py
pba_client/client.py
pba_client/exceptions.py
pba_client/apps/__init__.py
pba_client/apps/baza_gai.py
pba_client/apps/dto.py
pba_client/apps/helper_baza_gai.py
pba_client/apps/settings.py
pba_client/apps/telegram.py
tests/__init__.py
tests/test_car_number_api.py
tests/test_telegram_users_api.py
pba_client-0.0.7.dist-info/LICENSE
pba_client-0.0.7.dist-info/METADATA
pba_client-0.0.7.dist-info/WHEEL
pba_client-0.0.7.dist-info/top_level.txt
pba_client-0.0.7.dist-info/RECORD
