Metadata-Version: 2.1
Name: pba-client
Version: 0.0.7
Summary: Telegram Parking Bot (API Client)
Home-page: https://github.com/Humu-Social-KP/tg-parking-api-client
Author: Mykola Mozoliuk
Author-email: mmi200212@gmail.com
License: UNKNOWN
Project-URL: Bug Tracker, https://github.com/Humu-Social-KP/tg-parking-api-client/issues
Platform: UNKNOWN
Classifier: Programming Language :: Python :: 3
Classifier: License :: OSI Approved :: MIT License
Classifier: Operating System :: OS Independent
Requires-Python: >=3.6
License-File: LICENSE
